[
  {
    "id": 0,
    "title": "Estojo para Esterilização Perfurado Sterilys Pequeno com 2 - Lysanda",
    "price": "R$ 44,50",
    "href": "https://www.dentalecia.com.br/estjparaesterilizacaperfuradsterilyspequencm2lysanda/p",
    "img": "https://dentalecia.vteximg.com.br/arquivos/ids/158256-200-200/20200421135545_3773996227_G.jpg?v=637420211555230000",
    "time": {
      "stringifiedTimeData": "\"2021-01-24T19:33:08.869Z\"",
      "mins": 33,
      "hours": 16,
      "theDate": 24,
      "theMonth": 1,
      "theYear": 2021,
      "theDay": 0
    }
  },
  {
    "id": 1,
    "title": "Rolo Esterilização PackGC 80mm X 100m - Zermatt",
    "price": "R$ 46,90",
    "href": "https://www.dentalecia.com.br/rlesterilizacapackgc80mmx100mzermatt/p",
    "img": "https://dentalecia.vteximg.com.br/arquivos/ids/157746-200-200/Rolo-Esterilizacao-PackGC-80mm-X-100m---Zermatt.png?v=637420050262400000",
    "time": {
      "stringifiedTimeData": "\"2021-01-24T19:33:08.869Z\"",
      "mins": 33,
      "hours": 16,
      "theDate": 24,
      "theMonth": 1,
      "theYear": 2021,
      "theDay": 0
    }
  },
  {
    "id": 2,
    "title": "Rolo Esterilização PackGC 100mm X 100m - Zermatt",
    "price": "R$ 57,90",
    "href": "https://www.dentalecia.com.br/rlesterilizacapackgc100mmx100mzermatt/p",
    "img": "https://dentalecia.vteximg.com.br/arquivos/ids/157745-200-200/Rolo-Esterilizacao-PackGC-80mm-X-100m---Zermatt.png?v=637420049496770000",
    "time": {
      "stringifiedTimeData": "\"2021-01-24T19:33:08.869Z\"",
      "mins": 33,
      "hours": 16,
      "theDate": 24,
      "theMonth": 1,
      "theYear": 2021,
      "theDay": 0
    }
  },
  {
    "id": 3,
    "title": "Rolo Esterilização Pack GC 300mm x 100m - Zermatt",
    "price": "R$ 159,60",
    "href": "https://www.dentalecia.com.br/rlesterilizacapackgc300mmx100mzermatt/p",
    "img": "https://dentalecia.vteximg.com.br/arquivos/ids/168363-200-200/300x100.png?v=637469217955500000",
    "time": {
      "stringifiedTimeData": "\"2021-01-24T19:33:08.869Z\"",
      "mins": 33,
      "hours": 16,
      "theDate": 24,
      "theMonth": 1,
      "theYear": 2021,
      "theDay": 0
    }
  },
  {
    "id": 4,
    "title": "Rolo Esterilização Pack GC 200mm X 100m - Zermatt",
    "price": "R$ 109,90",
    "href": "https://www.dentalecia.com.br/rlesterilizacapackgc200mmx100mzermatt/p",
    "img": "https://dentalecia.vteximg.com.br/arquivos/ids/157739-200-200/Rolo-Esterilizacao-Pack-GC-200mm-X-100m---Zermatt.png?v=637420044449630000",
    "time": {
      "stringifiedTimeData": "\"2021-01-24T19:33:08.869Z\"",
      "mins": 33,
      "hours": 16,
      "theDate": 24,
      "theMonth": 1,
      "theYear": 2021,
      "theDay": 0
    }
  },
  {
    "id": 5,
    "title": "Rolo Esterilização Pack GC 150mm X 100m - Zermatt",
    "price": "R$ 83,12",
    "href": "https://www.dentalecia.com.br/rlesterilizacapackgc150mmx100mzermatt/p",
    "img": "https://dentalecia.vteximg.com.br/arquivos/ids/157741-200-200/Rolo-Esterilizacao-Pack-GC-150mm-X-100m---Zermatt.png?v=637420048096400000",
    "time": {
      "stringifiedTimeData": "\"2021-01-24T19:33:08.869Z\"",
      "mins": 33,
      "hours": 16,
      "theDate": 24,
      "theMonth": 1,
      "theYear": 2021,
      "theDay": 0
    }
  },
  {
    "id": 6,
    "title": "Estojo para Esterilização Perfurado Sterilys Grande - Lysanda",
    "price": "R$ 32,64",
    "href": "https://www.dentalecia.com.br/estjparaesterilizacaperfuradsterilysgrandelysanda/p",
    "img": "https://dentalecia.vteximg.com.br/arquivos/ids/158151-200-200/20200421142904_7338992662_G.jpg?v=637420160687470000",
    "time": {
      "stringifiedTimeData": "\"2021-01-24T19:33:08.869Z\"",
      "mins": 33,
      "hours": 16,
      "theDate": 24,
      "theMonth": 1,
      "theYear": 2021,
      "theDay": 0
    }
  },
  {
    "id": 7,
    "title": "Envelope Auto-Selante Grau Cirúrgico VedaMax 90x260mm - Zermatt",
    "price": "R$ 28,90",
    "href": "https://www.dentalecia.com.br/envelpeautselantegraucirurgicvedamax90x260mmzermatt/p",
    "img": "https://dentalecia.vteximg.com.br/arquivos/ids/168268-200-200/envelope-autosselante-packgc-9-cm-x-16-cm-com-100-unidades-zoom.jpg?v=637467715587930000",
    "time": {
      "stringifiedTimeData": "\"2021-01-24T19:33:08.869Z\"",
      "mins": 33,
      "hours": 16,
      "theDate": 24,
      "theMonth": 1,
      "theYear": 2021,
      "theDay": 0
    }
  },
  {
    "id": 8,
    "title": "Envelope Auto-Selante Grau Cirúrgico VedaMax 230x350mm - Zermatt",
    "price": "R$ 78,90",
    "href": "https://www.dentalecia.com.br/envelpeautselantegraucirurgicvedamax230x350mmzermatt/p",
    "img": "https://dentalecia.vteximg.com.br/arquivos/ids/168267-200-200/Papel-Grau-Cirurgico-Envelope-Zermatt-Autocolante-150x250mm-100un.jpg?v=637467714882200000",
    "time": {
      "stringifiedTimeData": "\"2021-01-24T19:33:08.869Z\"",
      "mins": 33,
      "hours": 16,
      "theDate": 24,
      "theMonth": 1,
      "theYear": 2021,
      "theDay": 0
    }
  }
]