[
 {
  "id": 0,
  "title": "Cimento Provisório Temp Bond NE - Kerr",
  "details": "Embalagem com 50g de Base + 15g de Catalisador + 1 Bloco de Mistura.",
  "price": "R$105,00",
  "href": "https://www.dentalcremer.com.br/cimento-provisorio-temp-bond-ne-kerr-292664.html",
  "time": {
   "stringifiedTimeData": "\"2021-07-20T13:45:58.454Z\"",
   "mins": 45,
   "hours": 10,
   "theDate": 20,
   "theMonth": 7,
   "theYear": 2021,
   "theDay": 2
  }
 },
 {
  "id": 1,
  "title": "Cimento Provisório Provicol - Voco",
  "details": "Kit com 25g de Base + 25g de Catalisador.",
  "price": "R$123,17",
  "href": "https://www.dentalcremer.com.br/cimento-provisorio-provicol-voco-384611.html",
  "time": {
   "stringifiedTimeData": "\"2021-07-20T13:45:58.454Z\"",
   "mins": 45,
   "hours": 10,
   "theDate": 20,
   "theMonth": 7,
   "theYear": 2021,
   "theDay": 2
  }
 },
 {
  "id": 2,
  "title": "Cimento Provisório Provitemp - Biodinâmica",
  "details": "Kit com 2,5g de Base + 2,5g de Catalisador + 6 bicos aplicadores.",
  "price": "R$82,72",
  "href": "https://www.dentalcremer.com.br/cimento-provisorio-provitemp-biodinamica-382495.html",
  "time": {
   "stringifiedTimeData": "\"2021-07-20T13:45:58.454Z\"",
   "mins": 45,
   "hours": 10,
   "theDate": 20,
   "theMonth": 7,
   "theYear": 2021,
   "theDay": 2
  }
 },
 {
  "id": 3,
  "title": "Hidróxido de Cálcio Hydropast com Iodofórmio - Biodinâmica",
  "details": "Embalagem com 2,5g.",
  "price": "R$35,21",
  "href": "https://www.dentalcremer.com.br/cimento-provisorio-hydropast-com-iodoformio-biodinamica-546446.html",
  "time": {
   "stringifiedTimeData": "\"2021-07-20T13:45:58.454Z\"",
   "mins": 45,
   "hours": 10,
   "theDate": 20,
   "theMonth": 7,
   "theYear": 2021,
   "theDay": 2
  }
 },
 {
  "id": 4,
  "title": "Hidróxido de Cálcio Hydropast - Biodinâmica",
  "details": "Embalagem com 2,5g.",
  "price": "R$29,74",
  "href": "https://www.dentalcremer.com.br/cimento-provisorio-hydropast-biodinamica-546439.html",
  "time": {
   "stringifiedTimeData": "\"2021-07-20T13:45:58.454Z\"",
   "mins": 45,
   "hours": 10,
   "theDate": 20,
   "theMonth": 7,
   "theYear": 2021,
   "theDay": 2
  }
 },
 {
  "id": 5,
  "title": "Cimento Provisório Pulpo-San Pó - SS White",
  "details": "Embalagem com 50g.",
  "price": "R$27,86",
  "href": "https://www.dentalcremer.com.br/cimento-provisorio-pulpo-san-po-ss-white-239072.html",
  "time": {
   "stringifiedTimeData": "\"2021-07-20T13:45:58.454Z\"",
   "mins": 45,
   "hours": 10,
   "theDate": 20,
   "theMonth": 7,
   "theYear": 2021,
   "theDay": 2
  }
 },
 {
  "id": 6,
  "title": "Cimento Provisório Pulpo-San Líquido - SS White",
  "details": "Embalagem com 20ml.",
  "price": "R$24,40",
  "href": "https://www.dentalcremer.com.br/cimento-provisorio-pulpo-san-liquido-ss-white-239089.html",
  "time": {
   "stringifiedTimeData": "\"2021-07-20T13:45:58.454Z\"",
   "mins": 45,
   "hours": 10,
   "theDate": 20,
   "theMonth": 7,
   "theYear": 2021,
   "theDay": 2
  }
 },
 {
  "id": 7,
  "title": "Cimento Provisório Provisory - Technew",
  "details": "Embalagem 50g de Base + 15g de Catalisador. Com Eugenol.",
  "price": "R$59,90",
  "href": "https://www.dentalcremer.com.br/cimento-provisorio-provisory-technew-345292.html",
  "time": {
   "stringifiedTimeData": "\"2021-07-20T13:45:58.454Z\"",
   "mins": 45,
   "hours": 10,
   "theDate": 20,
   "theMonth": 7,
   "theYear": 2021,
   "theDay": 2
  }
 }
]